booq/__init__.py
booq/__main__.py
booq/booq.py
booq/cli.py
booq-2022.8.9.dist-info/LICENSE
booq-2022.8.9.dist-info/METADATA
booq-2022.8.9.dist-info/WHEEL
booq-2022.8.9.dist-info/entry_points.txt
booq-2022.8.9.dist-info/top_level.txt
booq-2022.8.9.dist-info/RECORD
